{
  "type": "default",
  "events": [
    {
      "type": "minecraft:sound",
      "target": 0.1398,
      "data": {
        "sound": "gunsrpg:vector_mag1",
        "volume": 1.0,
        "pitch": 1.0,
        "direction": 0
      }
    },
    {
      "type": "minecraft:sound",
      "target": 0.5776,
      "data": {
        "sound": "gunsrpg:vector_mag2",
        "volume": 1.0,
        "pitch": 1.0,
        "direction": 0
      }
    },
    {
      "type": "minecraft:sound",
      "target": 0.8148,
      "data": {
        "sound": "gunsrpg:vector_ch1",
        "volume": 1.0,
        "pitch": 1.0,
        "direction": 0
      }
    }
  ],
  "data": {
    "minecraft:hands.right": [
      {
        "e": 0.0,
        "ease": 13
      },
      {
        "e": 0.13,
        "ease": 13,
        "rot": {
          "x": 10.0,
          "y": 0.0,
          "z": 0.0
        }
      },
      {
        "e": 0.2,
        "ease": 13,
        "pos": {
          "x": 0.0,
          "y": -0.05000000074505806,
          "z": 0.0
        },
        "rot": {
          "x": 10.0,
          "y": 0.0,
          "z": 0.0
        }
      },
      {
        "e": 0.35,
        "ease": 13,
        "rot": {
          "x": 10.0,
          "y": 0.0,
          "z": 0.0
        }
      },
      {
        "e": 0.62,
        "ease": 13,
        "pos": {
          "x": 0.0,
          "y": -0.019999999552965164,
          "z": 0.0
        },
        "rot": {
          "x": 10.0,
          "y": 0.0,
          "z": 0.0
        }
      },
      {
        "e": 0.67,
        "ease": 13,
        "pos": {
          "x": 0.0,
          "y": 0.009999999776482582,
          "z": 0.0
        },
        "rot": {
          "x": 10.0,
          "y": 0.0,
          "z": 0.0
        }
      },
      {
        "e": 0.71,
        "ease": 13,
        "pos": {
          "x": 0.0,
          "y": -0.019999999552965164,
          "z": 0.0
        },
        "rot": {
          "x": 10.0,
          "y": 0.0,
          "z": 0.0
        }
      },
      {
        "e": 0.8,
        "ease": 13,
        "pos": {
          "x": 0.0,
          "y": 0.0,
          "z": 0.05000000074505806
        },
        "rot": {
          "x": 10.0,
          "y": 0.0,
          "z": 0.0
        }
      },
      {
        "e": 0.85,
        "ease": 18,
        "pos": {
          "x": 0.009999999776482582,
          "y": 0.0,
          "z": 0.05000000074505806
        },
        "rot": {
          "x": 10.0,
          "y": 0.0,
          "z": 0.0
        }
      },
      {
        "e": 0.9,
        "ease": 13,
        "pos": {
          "x": 0.0,
          "y": 0.0,
          "z": 0.05000000074505806
        },
        "rot": {
          "x": 10.0,
          "y": 0.0,
          "z": 0.0
        }
      },
      {
        "e": 1.0,
        "ease": 13
      }
    ],
    "minecraft:hands.left": [
      {
        "e": 0.0,
        "ease": 13
      },
      {
        "e": 0.13,
        "ease": 13,
        "pos": {
          "x": 0.05000000074505806,
          "y": -0.05000000074505806,
          "z": 0.10000000149011612
        }
      },
      {
        "e": 0.22,
        "ease": 13,
        "pos": {
          "x": 0.05000000074505806,
          "y": -0.44999998807907104,
          "z": 0.10000000149011612
        }
      },
      {
        "e": 0.52,
        "ease": 13,
        "pos": {
          "x": 0.05000000074505806,
          "y": -0.44999998807907104,
          "z": 0.10000000149011612
        }
      },
      {
        "e": 0.62,
        "ease": 13,
        "pos": {
          "x": 0.05000000074505806,
          "y": -0.05000000074505806,
          "z": 0.10000000149011612
        }
      },
      {
        "e": 0.67,
        "ease": 13,
        "pos": {
          "x": 0.05000000074505806,
          "y": -0.019999999552965164,
          "z": 0.10000000149011612
        }
      },
      {
        "e": 0.71,
        "ease": 13,
        "pos": {
          "x": 0.05000000074505806,
          "y": -0.05000000074505806,
          "z": 0.10000000149011612
        }
      },
      {
        "e": 0.8,
        "ease": 13,
        "pos": {
          "x": -0.10000000149011612,
          "y": 0.2199999988079071,
          "z": 0.2199999988079071
        }
      },
      {
        "e": 0.85,
        "ease": 18,
        "pos": {
          "x": -0.05000000074505806,
          "y": 0.2199999988079071,
          "z": 0.2199999988079071
        }
      },
      {
        "e": 0.9,
        "ease": 13,
        "pos": {
          "x": -0.07999999821186066,
          "y": 0.2199999988079071,
          "z": 0.2199999988079071
        }
      },
      {
        "e": 1.0,
        "ease": 13
      }
    ],
    "minecraft:item.heldfp": [
      {
        "e": 0.0,
        "ease": 13
      },
      {
        "e": 0.13,
        "ease": 13,
        "rot": {
          "x": 10.0,
          "y": 0.0,
          "z": 0.0
        }
      },
      {
        "e": 0.2,
        "ease": 13,
        "pos": {
          "x": 0.0,
          "y": -0.05000000074505806,
          "z": 0.0
        },
        "rot": {
          "x": 10.0,
          "y": 0.0,
          "z": 0.0
        }
      },
      {
        "e": 0.35,
        "ease": 13,
        "rot": {
          "x": 10.0,
          "y": 0.0,
          "z": 0.0
        }
      },
      {
        "e": 0.62,
        "ease": 13,
        "pos": {
          "x": 0.0,
          "y": -0.019999999552965164,
          "z": 0.0
        },
        "rot": {
          "x": 10.0,
          "y": 0.0,
          "z": 0.0
        }
      },
      {
        "e": 0.67,
        "ease": 13,
        "pos": {
          "x": 0.0,
          "y": 0.009999999776482582,
          "z": 0.0
        },
        "rot": {
          "x": 10.0,
          "y": 0.0,
          "z": 0.0
        }
      },
      {
        "e": 0.71,
        "ease": 13,
        "pos": {
          "x": 0.0,
          "y": -0.019999999552965164,
          "z": 0.0
        },
        "rot": {
          "x": 10.0,
          "y": 0.0,
          "z": 0.0
        }
      },
      {
        "e": 0.8,
        "ease": 13,
        "pos": {
          "x": 0.0,
          "y": 0.0,
          "z": 0.05000000074505806
        },
        "rot": {
          "x": 10.0,
          "y": 0.0,
          "z": 0.0
        }
      },
      {
        "e": 0.85,
        "ease": 18,
        "pos": {
          "x": 0.009999999776482582,
          "y": 0.0,
          "z": 0.05000000074505806
        },
        "rot": {
          "x": 10.0,
          "y": 0.0,
          "z": 0.0
        }
      },
      {
        "e": 0.9,
        "ease": 13,
        "pos": {
          "x": 0.0,
          "y": 0.0,
          "z": 0.05000000074505806
        },
        "rot": {
          "x": 10.0,
          "y": 0.0,
          "z": 0.0
        }
      },
      {
        "e": 1.0,
        "ease": 13
      }
    ],
    "gunsrpg:weapon.magazine": [
      {
        "e": 0.0,
        "ease": 13
      },
      {
        "e": 0.13,
        "ease": 13
      },
      {
        "e": 0.22,
        "ease": 13,
        "pos": {
          "x": 0.0,
          "y": 2.0,
          "z": 0.5
        }
      },
      {
        "e": 0.52,
        "ease": 13,
        "pos": {
          "x": 0.0,
          "y": 2.0,
          "z": 0.5
        }
      },
      {
        "e": 0.62,
        "ease": 13
      },
      {
        "e": 0.67,
        "ease": 13
      }
    ]
  }
}